Workbook

Sheet Lee esto
A1: Qué es: un modelo para decidir, no una previsión.
A2: Todo lo amarillo es una hipótesis. No hay clientes de pago todavía (celda verde).
A3: Cómo usarlo: cambia los supuestos en la hoja «Supuestos»; las tres hojas de escenario se recalculan solas.
A4: Qué no incluye: IVA, impuestos sobre beneficios, sueldos del titular, publicidad de pago, costes de WhatsApp (no se ofrece todavía).
A5: Antes de usarlo para pedir financiación o fijar precios: sustituir las hipótesis por datos de los pilotos (soporte real, conversión real, bajas reales).

Sheet Supuestos
A1: Repite · Modelo financiero inicial (EDITABLE)
A2: Celdas amarillas = HIPÓTESIS (cámbialas). Verde = dato verificado. Importes en EUR, sin IVA. Revisar precios de proveedores antes de contratar.
A4: Supuesto | B4: Conservador | C4: Base | D4: Optimista | E4: Tipo | F4: Nota
A5: Nuevos clientes de pago en el mes 1 | B5: 1 | C5: 2 | D5: 4 | E5: hipótesis | F5: Clientes que pasan a pagar tras la prueba
A6: Crecimiento mensual de altas (%) | B6: 0.1 | C6: 0.15 | D6: 0.2 | E6: hipótesis | F6: Sobre las altas del mes anterior
A7: Bajas mensuales (churn, %) | B7: 0.08 | C7: 0.05 | D7: 0.03 | E7: hipótesis | F7: Sobre clientes activos
A8: % de clientes en Growth | B8: 0.15 | C8: 0.25 | D8: 0.35 | E8: hipótesis | F8: El resto está en Esencial
A9: Precio Esencial (€/mes) | B9: 25 | C9: 25 | D9: 25 | E9: hipótesis | F9: A validar con pilotos
A10: Precio Growth (€/mes) | B10: 49 | C10: 49 | D10: 49 | E10: hipótesis | F10: A validar con pilotos
A11: Coste de adquisición por cliente (€) | B11: 120 | C11: 90 | D11: 60 | E11: hipótesis | F11: Tiempo comercial + material; sin publicidad de pago
A12: Minutos de soporte por cliente y mes | B12: 45 | C12: 30 | D12: 20 | E12: hipótesis | F12: Medir en pilotos
A13: Coste hora de soporte (€) | B13: 20 | C13: 20 | D13: 20 | E13: hipótesis | F13: Coste interno estimado
A14: Comisión de cobro (% sobre ingreso) | B14: 0.015 | C14: 0.015 | D14: 0.015 | E14: hipótesis | F14: Tarifa estándar de tarjetas europeas del proveedor de cobro: verificar
A15: Comisión fija por cobro (€) | B15: 0.25 | C15: 0.25 | D15: 0.25 | E15: hipótesis | F15: Idem; verificar
A16: Hosting web (€/mes) | B16: 19 | C16: 19 | D16: 19 | E16: hipótesis | F16: Plan de pago del proveedor de despliegue (≈20 USD): verificar
... A23: Clientes de pago hoy | B23: 0 | C23: 0 | D23: 0 | E23: verificado | F23: Producción: 0 organizaciones a 25-oct-2026

Sheet Conservador
A1: Escenario Conservador · 12 primeros meses
A3: Mes | B3: Altas | C3: Bajas | D3: Clientes activos | E3: MRR (€) | F3: Comisiones de cobro (€) | G3: Soporte (€) | H3: Costes fijos (€) | I3: Adquisición (€) | J3: Resultado del mes (€) | K3: Resultado acumulado (€) | L3: Margen bruto (%)
A4: 1 | B4: =Supuestos!$B$5*(1+Supuestos!$B$6)^(1-1) -> 1 | C4: =0 -> 0 | D4: =B4-C4 -> 1 | E4: =D4*((1-Supuestos!$B$8)*Supuestos!$B$9+Supuestos!$B$8*Supuestos!$B$10) -> 28.6 | F4: =E4*Supuestos!$B$14+D4*Supuestos!$B$15 -> 0.679 | G4: =D4*Supuestos!$B$12/60*Supuestos!$B$13 -> 15 | H4: =Supuestos!$B$16+Supuestos!$B$17+Supuestos!$B$18+Supuestos!$B$19+Supuestos!$B$20+Supuestos!$B$21 -> 135 | I4: =B4*Supuestos!$B$11 -> 120 | J4: =E4-F4-G4-H4-I4-Supuestos!$B$22 -> -3242.079 | K4: =J4 -> -3242.079 | L4: =IF(E4=0,0,(E4-F4-G4)/E4) -> 0.45178322
A5: 2 | B5: =Supuestos!$B$5*(1+Supuestos!$B$6)^(2-1) -> 1.1 | C5: =D4*Supuestos!$B$7 -> 0.08 | D5: =D4+B5-C5 -> 2.02 | E5: =D5*((1-Supuestos!$B$8)*Supuestos!$B$9+Supuestos!$B$8*Supuestos!$B$10) -> 57.772 | F5: =E5*Supuestos!$B$14+D5*Supuestos!$B$15 -> 1.37158 | G5: =D5*Supuestos!$B$12/60*Supuestos!$B$13 -> 30.3 | H5: =Supuestos!$B$16+Supuestos!$B$17+Supuestos!$B$18+Supuestos!$B$19+Supuestos!$B$20+Supuestos!$B$21 -> 135 | I5: =B5*Supuestos!$B$11 -> 132 | J5: =E5-F5-G5-H5-I5 -> -240.89958 | K5: =K4+J5 -> -3482.9786 | L5: =IF(E5=0,0,(E5-F5-G5)/E5) -> 0.45178322
A6: 3 | B6: =Supuestos!$B$5*(1+Supuestos!$B$6)^(3-1) -> 1.21 | C6: =D5*Supuestos!$B$7 -> 0.1616 | D6: =D5+B6-C6 -> 3.0684 | E6: =D6*((1-Supuestos!$B$8)*Supuestos!$B$9+Supuestos!$B$8*Supuestos!$B$10) -> 87.75624 | F6: =E6*Supuestos!$B$14+D6*Supuestos!$B$15 -> 2.0834436 | G6: =D6*Supuestos!$B$12/60*Supuestos!$B$13 -> 46.026 | H6: =Supuestos!$B$16+Supuestos!$B$17+Supuestos!$B$18+Supuestos!$B$19+Supuestos!$B$20+Supuestos!$B$21 -> 135 | I6: =B6*Supuestos!$B$11 -> 145.2 | J6: =E6-F6-G6-H6-I6 -> -240.5532 | K6: =K5+J6 -> -3723.5318 | L6: =IF(E6=0,0,(E6-F6-G6)/E6) -> 0.45178322
A7: 4 | B7: =Supuestos!$B$5*(1+Supuestos!$B$6)^(4-1) -> 1.331 | C7: =D6*Supuestos!$B$7 -> 0.245472 | D7: =D6+B7-C7 -> 4.153928 | E7: =D7*((1-Supuestos!$B$8)*Supuestos!$B$9+Supuestos!$B$8*Supuestos!$B$10) -> 118.80234 | F7: =E7*Supuestos!$B$14+D7*Supuestos!$B$15 -> 2.8205171 | G7: =D7*Supuestos!$B$12/60*Supuestos!$B$13 -> 62.30892 | H7: =Supuestos!$B$16+Supuestos!$B$17+Supuestos!$B$18+Supuestos!$B$19+Supuestos!$B$20+Supuestos!$B$21 -> 135 | I7: =B7*Supuestos!$B$11 -> 159.72 | J7: =E7-F7-G7-H7-I7 -> -241.0471 | K7: =K6+J7 -> -3964.5789 | L7: =IF(E7=0,0,(E7-F7-G7)/E7) -> 0.45178322
A8: 5 | B8: =Supuestos!$B$5*(1+Supuestos!$B$6)^(5-1) -> 1.4641 | C8: =D7*Supuestos!$B$7 -> 0.33231424 | D8: =D7+B8-C8 -> 5.2857138 | E8: =D8*((1-Supuestos!$B$8)*Supuestos!$B$9+Supuestos!$B$8*Supuestos!$B$10) -> 151.17141 | F8: =E8*Supuestos!$B$14+D8*Supuestos!$B$15 -> 3.5889996 | G8: =D8*Supuestos!$B$12/60*Supuestos!$B$13 -> 79.285706 | H8: =Supuestos!$B$16+Supuestos!$B$17+Supuestos!$B$18+Supuestos!$B$19+Supuestos!$B$20+Supuestos!$B$21 -> 135 | I8: =B8*Supuestos!$B$11 -> 175.692 | J8: =E8-F8-G8-H8-I8 -> -242.39529 | K8: =K7+J8 -> -4206.9742 | L8: =IF(E8=0,0,(E8-F8-G8)/E8) -> 0.45178322
A9: 6 | B9: =Supuestos!$B$5*(1+Supuestos!$B$6)^(6-1) -> 1.61051 | C9: =D8*Supuestos!$B$7 -> 0.4228571 | D9: =D8+B9-C9 -> 6.4733667 | E9: =D9*((1-Supuestos!$B$8)*Supuestos!$B$9+Supuestos!$B$8*Supuestos!$B$10) -> 185.13829 | F9: =E9*Supuestos!$B$14+D9*Supuestos!$B$15 -> 4.395416 | G9: =D9*Supuestos!$B$12/60*Supuestos!$B$13 -> 97.1005 | H9: =Supuestos!$B$16+Supuestos!$B$17+Supuestos!$B$18+Supuestos!$B$19+Supuestos!$B$20+Supuestos!$B$21 -> 135 | I9: =B9*Supuestos!$B$11 -> 193.2612 | J9: =E9-F9-G9-H9-I9 -> -244.61883 | K9: =K8+J9 -> -4451.593 | L9: =IF(E9=0,0,(E9-F9-G9)/E9) -> 0.45178322
A10: 7 | B10: =Supuestos!$B$5*(1+Supuestos!$B$6)^(7-1) -> 1.771561 | C10: =D9*Supuestos!$B$7 -> 0.51786933 | D10: =D9+B10-C10 -> 7.7270583 | E10: =D10*((1-Supuestos!$B$8)*Supuestos!$B$9+Supuestos!$B$8*Supuestos!$B$10) -> 220.99387 | F10: =E10*Supuestos!$B$14+D10*Supuestos!$B$15 -> 5.2466726 | G10: =D10*Supuestos!$B$12/60*Supuestos!$B$13 -> 115.90587 | H10: =Supuestos!$B$16+Supuestos!$B$17+Supuestos!$B$18+Supuestos!$B$19+Supuestos!$B$20+Supuestos!$B$21 -> 135 | I10: =B10*Supuestos!$B$11 -> 212.58732 | J10: =E10-F10-G10-H10-I10 -> -247.746 | K10: =K9+J10 -> -4699.339 | L10: =IF(E10=0,0,(E10-F10-G10)/E10) -> 0.45178322
A11: 8 | B11: =Supuestos!$B$5*(1+Supuestos!$B$6)^(8-1) -> 1.9487171 | C11: =D10*Supuestos!$B$7 -> 0.61816467 | D11: =D10+B11-C11 -> 9.0576108 | E11: =D11*((1-Supuestos!$B$8)*Supuestos!$B$9+Supuestos!$B$8*Supuestos!$B$10) -> 259.04767 | F11: =E11*Supuestos!$B$14+D11*Supuestos!$B$15 -> 6.1501177 | G11: =D11*Supuestos!$B$12/60*Supuestos!$B$13 -> 135.86416 | H11: =Supuestos!$B$16+Supuestos!$B$17+Supuestos!$B$18+Supuestos!$B$19+Supuestos!$B$20+Supuestos!$B$21 -> 135 | I11: =B11*Supuestos!$B$11 -> 233.84605 | J11: =E11-F11-G11-H11-I11 -> -251.81266 | K11: =K10+J11 -> -4951.1517 | L11: =IF(E11=0,0,(E11-F11-G11)/E11) -> 0.45178322
A12: 9 | B12: =Supuestos!$B$5*(1+Supuestos!$B$6)^(9-1) -> 2.1435888 | C12: =D11*Supuestos!$B$7 -> 0.72460886 | D12: =D11+B12-C12 -> 10.476591 | E12: =D12*((1-Supuestos!$B$8)*Supuestos!$B$9+Supuestos!$B$8*Supuestos!$B$10) -> 299.63049 | F12: =E12*Supuestos!$B$14+D12*Supuestos!$B$15 -> 7.1136051 | G12: =D12*Supuestos!$B$12/60*Supuestos!$B$13 -> 157.14886 | H12: =Supuestos!$B$16+Supuestos!$B$17+Supuestos!$B$18+Supuestos!$B$19+Supuestos!$B$20+Supuestos!$B$21 -> 135 | I12: =B12*Supuestos!$B$11 -> 257.23066 | J12: =E12-F12-G12-H12-I12 -> -256.86263 | K12: =K11+J12 -> -5208.0143 | L12: =IF(E12=0,0,(E12-F12-G12)/E12) -> 0.45178322
A13: 10 | B13: =Supuestos!$B$5*(1+Supuestos!$B$6)^(10-1) -> 2.3579477 | C13: =D12*Supuestos!$B$7 -> 0.83812726 | D13: =D12+B13-C13 -> 11.996411 | E13: =D13*((1-Supuestos!$B$8)*Supuestos!$B$9+Supuestos!$B$8*Supuestos!$B$10) -> 343.09736 | F13: =E13*Supuestos!$B$14+D13*Supuestos!$B$15 -> 8.1455632 | G13: =D13*Supuestos!$B$12/60*Supuestos!$B$13 -> 179.94617 | H13: =Supuestos!$B$16+Supuestos!$B$17+Supuestos!$B$18+Supuestos!$B$19+Supuestos!$B$20+Supuestos!$B$21 -> 135 | I13: =B13*Supuestos!$B$11 -> 282.95372 | J13: =E13-F13-G13-H13-I13 -> -262.94809 | K13: =K12+J13 -> -5470.9624 | L13: =IF(E13=0,0,(E13-F13-G13)/E13) -> 0.45178322
A14: 11 | B14: =Supuestos!$B$5*(1+Supuestos!$B$6)^(11-1) -> 2.5937425 | C14: =D13*Supuestos!$B$7 -> 0.95971289 | D14: =D13+B14-C14 -> 13.630441 | E14: =D14*((1-Supuestos!$B$8)*Supuestos!$B$9+Supuestos!$B$8*Supuestos!$B$10) -> 389.8306 | F14: =E14*Supuestos!$B$14+D14*Supuestos!$B$15 -> 9.2550692 | G14: =D14*Supuestos!$B$12/60*Supuestos!$B$13 -> 204.45661 | H14: =Supuestos!$B$16+Supuestos!$B$17+Supuestos!$B$18+Supuestos!$B$19+Supuestos!$B$20+Supuestos!$B$21 -> 135 | I14: =B14*Supuestos!$B$11 -> 311.2491 | J14: =E14-F14-G14-H14-I14 -> -270.13017 | K14: =K13+J14 -> -5741.0926 | L14: =IF(E14=0,0,(E14-F14-G14)/E14) -> 0.45178322
A15: 12 | B15: =Supuestos!$B$5*(1+Supuestos!$B$6)^(12-1) -> 2.8531167 | C15: =D14*Supuestos!$B$7 -> 1.0904353 | D15: =D14+B15-C15 -> 15.393122 | E15: =D15*((1-Supuestos!$B$8)*Supuestos!$B$9+Supuestos!$B$8*Supuestos!$B$10) -> 440.24329 | F15: =E15*Supuestos!$B$14+D15*Supuestos!$B$15 -> 10.45193 | G15: =D15*Supuestos!$B$12/60*Supuestos!$B$13 -> 230.89683 | H15: =Supuestos!$B$16+Supuestos!$B$17+Supuestos!$B$18+Supuestos!$B$19+Supuestos!$B$20+Supuestos!$B$21 -> 135 | I15: =B15*Supuestos!$B$11 -> 342.374 | J15: =E15-F15-G15-H15-I15 -> -278.47947 | K15: =K14+J15 -> -6019.572 | L15: =IF(E15=0,0,(E15-F15-G15)/E15) -> 0.45178322
A17: Resumen
A18: MRR al mes 12 (€) | B18: =E15 -> 440.24329
A19: ARR (MRR × 12, €) | B19: =B18*12 -> 5282.9195
A20: Clientes activos al mes 12 | B20: =D15 -> 15.393122
A21: Resultado acumulado al mes 12 (€) | B21: =K15 -> -6019.572
A22: Primer mes con resultado mensual positivo | B22: =IFERROR(INDEX(A4:A15,MATCH(TRUE(),INDEX(J4:J15>0,0),0)),"no en 12 meses") -> no en 12 meses
A23: Ingreso medio por cliente (€/mes) | B23: =((1-Supuestos!$B$8)*Supuestos!$B$9+Supuestos!$B$8*Supuestos!$B$10) -> 28.6
A24: Recuperación del coste de adquisición (meses) | B24: =IFERROR(Supuestos!$B$11/(((1-Supuestos!$B$8)*Supuestos!$B$9+Supuestos!$B$8*Supuestos!$B$10)*(1-Supuestos!$B$14)-Supuestos!$B$15-Supuestos!$B$12/60*Supuestos!$B$13),"n/d") -> 9.2872069

Sheet Base
A1: Escenario Base · 12 primeros meses
A3: Mes | B3: Altas | C3: Bajas | D3: Clientes activos | E3: MRR (€) | F3: Comisiones de cobro (€) | G3: Soporte (€) | H3: Costes fijos (€) | I3: Adquisición (€) | J3: Resultado del mes (€) | K3: Resultado acumulado (€) | L3: Margen bruto (%)
A4: 1 | B4: =Supuestos!$C$5*(1+Supuestos!$C$6)^(1-1) -> 2 | C4: =0 -> 0 | D4: =B4-C4 -> 2 | E4: =D4*((1-Supuestos!$C$8)*Supuestos!$C$9+Supuestos!$C$8*Supuestos!$C$10) -> 62 | F4: =E4*Supuestos!$C$14+D4*Supuestos!$C$15 -> 1.43 | G4: =D4*Supuestos!$C$12/60*Supuestos!$C$13 -> 20 | H4: =Supuestos!$C$16+Supuestos!$C$17+Supuestos!$C$18+Supuestos!$C$19+Supuestos!$C$20+Supuestos!$C$21 -> 135 | I4: =B4*Supuestos!$C$11 -> 180 | J4: =E4-F4-G4-H4-I4-Supuestos!$C$22 -> -3274.43 | K4: =J4 -> -3274.43 | L4: =IF(E4=0,0,(E4-F4-G4)/E4) -> 0.65435484
A5: 2 | B5: =Supuestos!$C$5*(1+Supuestos!$C$6)^(2-1) -> 2.3 | C5: =D4*Supuestos!$C$7 -> 0.1 | D5: =D4+B5-C5 -> 4.2 | E5: =D5*((1-Supuestos!$C$8)*Supuestos!$C$9+Supuestos!$C$8*Supuestos!$C$10) -> 130.2 | F5: =E5*Supuestos!$C$14+D5*Supuestos!$C$15 -> 3.003 | G5: =D5*Supuestos!$C$12/60*Supuestos!$C$13 -> 42 | H5: =Supuestos!$C$16+Supuestos!$C$17+Supuestos!$C$18+Supuestos!$C$19+Supuestos!$C$20+Supuestos!$C$21 -> 135 | I5: =B5*Supuestos!$C$11 -> 207 | J5: =E5-F5-G5-H5-I5 -> -256.803 | K5: =K4+J5 -> -3531.233 | L5: =IF(E5=0,0,(E5-F5-G5)/E5) -> 0.65435484
A6: 3 | B6: =Supuestos!$C$5*(1+Supuestos!$C$6)^(3-1) -> 2.645 | C6: =D5*Supuestos!$C$7 -> 0.21 | D6: =D5+B6-C6 -> 6.635 | E6: =D6*((1-Supuestos!$C$8)*Supuestos!$C$9+Supuestos!$C$8*Supuestos!$C$10) -> 205.685 | F6: =E6*Supuestos!$C$14+D6*Supuestos!$C$15 -> 4.744025 | G6: =D6*Supuestos!$C$12/60*Supuestos!$C$13 -> 66.35 | H6: =Supuestos!$C$16+Supuestos!$C$17+Supuestos!$C$18+Supuestos!$C$19+Supuestos!$C$20+Supuestos!$C$21 -> 135 | I6: =B6*Supuestos!$C$11 -> 238.05 | J6: =E6-F6-G6-H6-I6 -> -238.45902 | K6: =K5+J6 -> -3769.692 | L6: =IF(E6=0,0,(E6-F6-G6)/E6) -> 0.65435484
A7: 4 | B7: =Supuestos!$C$5*(1+Supuestos!$C$6)^(4-1) -> 3.04175 | C7: =D6*Supuestos!$C$7 -> 0.33175 | D7: =D6+B7-C7 -> 9.345 | E7: =D7*((1-Supuestos!$C$8)*Supuestos!$C$9+Supuestos!$C$8*Supuestos!$C$10) -> 289.695 | F7: =E7*Supuestos!$C$14+D7*Supuestos!$C$15 -> 6.681675 | G7: =D7*Supuestos!$C$12/60*Supuestos!$C$13 -> 93.45 | H7: =Supuestos!$C$16+Supuestos!$C$17+Supuestos!$C$18+Supuestos!$C$19+Supuestos!$C$20+Supuestos!$C$21 -> 135 | I7: =B7*Supuestos!$C$11 -> 273.7575 | J7: =E7-F7-G7-H7-I7 -> -219.19418 | K7: =K6+J7 -> -3988.8862 | L7: =IF(E7=0,0,(E7-F7-G7)/E7) -> 0.65435484
A8: 5 | B8: =Supuestos!$C$5*(1+Supuestos!$C$6)^(5-1) -> 3.4980125 | C8: =D7*Supuestos!$C$7 -> 0.46725 | D8: =D7+B8-C8 -> 12.375763 | E8: =D8*((1-Supuestos!$C$8)*Supuestos!$C$9+Supuestos!$C$8*Supuestos!$C$10) -> 383.64864 | F8: =E8*Supuestos!$C$14+D8*Supuestos!$C$15 -> 8.8486702 | G8: =D8*Supuestos!$C$12/60*Supuestos!$C$13 -> 123.75763 | H8: =Supuestos!$C$16+Supuestos!$C$17+Supuestos!$C$18+Supuestos!$C$19+Supuestos!$C$20+Supuestos!$C$21 -> 135 | I8: =B8*Supuestos!$C$11 -> 314.82112 | J8: =E8-F8-G8-H8-I8 -> -198.77878 | K8: =K7+J8 -> -4187.665 | L8: =IF(E8=0,0,(E8-F8-G8)/E8) -> 0.65435484
A9: 6 | B9: =Supuestos!$C$5*(1+Supuestos!$C$6)^(6-1) -> 4.0227144 | C9: =D8*Supuestos!$C$7 -> 0.61878813 | D9: =D8+B9-C9 -> 15.779689 | E9: =D9*((1-Supuestos!$C$8)*Supuestos!$C$9+Supuestos!$C$8*Supuestos!$C$10) -> 489.17035 | F9: =E9*Supuestos!$C$14+D9*Supuestos!$C$15 -> 11.282477 | G9: =D9*Supuestos!$C$12/60*Supuestos!$C$13 -> 157.79689 | H9: =Supuestos!$C$16+Supuestos!$C$17+Supuestos!$C$18+Supuestos!$C$19+Supuestos!$C$20+Supuestos!$C$21 -> 135 | I9: =B9*Supuestos!$C$11 -> 362.04429 | J9: =E9-F9-G9-H9-I9 -> -176.95331 | K9: =K8+J9 -> -4364.6183 | L9: =IF(E9=0,0,(E9-F9-G9)/E9) -> 0.65435484
A10: 7 | B10: =Supuestos!$C$5*(1+Supuestos!$C$6)^(7-1) -> 4.6261215 | C10: =D9*Supuestos!$C$7 -> 0.78898444 | D10: =D9+B10-C10 -> 19.616826 | E10: =D10*((1-Supuestos!$C$8)*Supuestos!$C$9+Supuestos!$C$8*Supuestos!$C$10) -> 608.1216 | F10: =E10*Supuestos!$C$14+D10*Supuestos!$C$15 -> 14.02603 | G10: =D10*Supuestos!$C$12/60*Supuestos!$C$13 -> 196.16826 | H10: =Supuestos!$C$16+Supuestos!$C$17+Supuestos!$C$18+Supuestos!$C$19+Supuestos!$C$20+Supuestos!$C$21 -> 135 | I10: =B10*Supuestos!$C$11 -> 416.35094 | J10: =E10-F10-G10-H10-I10 -> -153.42363 | K10: =K9+J10 -> -4518.0419 | L10: =IF(E10=0,0,(E10-F10-G10)/E10) -> 0.65435484
A11: 8 | B11: =Supuestos!$C$5*(1+Supuestos!$C$6)^(8-1) -> 5.3200398 | C11: =D10*Supuestos!$C$7 -> 0.98084129 | D11: =D10+B11-C11 -> 23.956024 | E11: =D11*((1-Supuestos!$C$8)*Supuestos!$C$9+Supuestos!$C$8*Supuestos!$C$10) -> 742.63675 | F11: =E11*Supuestos!$C$14+D11*Supuestos!$C$15 -> 17.128557 | G11: =D11*Supuestos!$C$12/60*Supuestos!$C$13 -> 239.56024 | H11: =Supuestos!$C$16+Supuestos!$C$17+Supuestos!$C$18+Supuestos!$C$19+Supuestos!$C$20+Supuestos!$C$21 -> 135 | I11: =B11*Supuestos!$C$11 -> 478.80358 | J11: =E11-F11-G11-H11-I11 -> -127.85563 | K11: =K10+J11 -> -4645.8975 | L11: =IF(E11=0,0,(E11-F11-G11)/E11) -> 0.65435484
A12: 9 | B12: =Supuestos!$C$5*(1+Supuestos!$C$6)^(9-1) -> 6.1180457 | C12: =D11*Supuestos!$C$7 -> 1.1978012 | D12: =D11+B12-C12 -> 28.876269 | E12: =D12*((1-Supuestos!$C$8)*Supuestos!$C$9+Supuestos!$C$8*Supuestos!$C$10) -> 895.16433 | F12: =E12*Supuestos!$C$14+D12*Supuestos!$C$15 -> 20.646532 | G12: =D12*Supuestos!$C$12/60*Supuestos!$C$13 -> 288.76269 | H12: =Supuestos!$C$16+Supuestos!$C$17+Supuestos!$C$18+Supuestos!$C$19+Supuestos!$C$20+Supuestos!$C$21 -> 135 | I12: =B12*Supuestos!$C$11 -> 550.62412 | J12: =E12-F12-G12-H12-I12 -> -99.869002 | K12: =K11+J12 -> -4745.7665 | L12: =IF(E12=0,0,(E12-F12-G12)/E12) -> 0.65435484
A13: 10 | B13: =Supuestos!$C$5*(1+Supuestos!$C$6)^(10-1) -> 7.0357526 | C13: =D12*Supuestos!$C$7 -> 1.4438134 | D13: =D12+B13-C13 -> 34.468208 | E13: =D13*((1-Supuestos!$C$8)*Supuestos!$C$9+Supuestos!$C$8*Supuestos!$C$10) -> 1068.5144 | F13: =E13*Supuestos!$C$14+D13*Supuestos!$C$15 -> 24.644769 | G13: =D13*Supuestos!$C$12/60*Supuestos!$C$13 -> 344.68208 | H13: =Supuestos!$C$16+Supuestos!$C$17+Supuestos!$C$18+Supuestos!$C$19+Supuestos!$C$20+Supuestos!$C$21 -> 135 | I13: =B13*Supuestos!$C$11 -> 633.21773 | J13: =E13-F13-G13-H13-I13 -> -69.030134 | K13: =K12+J13 -> -4814.7967 | L13: =IF(E13=0,0,(E13-F13-G13)/E13) -> 0.65435484
A14: 11 | B14: =Supuestos!$C$5*(1+Supuestos!$C$6)^(11-1) -> 8.0911155 | C14: =D13*Supuestos!$C$7 -> 1.7234104 | D14: =D13+B14-C14 -> 40.835913 | E14: =D14*((1-Supuestos!$C$8)*Supuestos!$C$9+Supuestos!$C$8*Supuestos!$C$10) -> 1265.9133 | F14: =E14*Supuestos!$C$14+D14*Supuestos!$C$15 -> 29.197678 | G14: =D14*Supuestos!$C$12/60*Supuestos!$C$13 -> 408.35913 | H14: =Supuestos!$C$16+Supuestos!$C$17+Supuestos!$C$18+Supuestos!$C$19+Supuestos!$C$20+Supuestos!$C$21 -> 135 | I14: =B14*Supuestos!$C$11 -> 728.20039 | J14: =E14-F14-G14-H14-I14 -> -34.843896 | K14: =K13+J14 -> -4849.6406 | L14: =IF(E14=0,0,(E14-F14-G14)/E14) -> 0.65435484
A15: 12 | B15: =Supuestos!$C$5*(1+Supuestos!$C$6)^(12-1) -> 9.3047828 | C15: =D14*Supuestos!$C$7 -> 2.0417957 | D15: =D14+B15-C15 -> 48.0989 | E15: =D15*((1-Supuestos!$C$8)*Supuestos!$C$9+Supuestos!$C$8*Supuestos!$C$10) -> 1491.0659 | F15: =E15*Supuestos!$C$14+D15*Supuestos!$C$15 -> 34.390714 | G15: =D15*Supuestos!$C$12/60*Supuestos!$C$13 -> 480.989 | H15: =Supuestos!$C$16+Supuestos!$C$17+Supuestos!$C$18+Supuestos!$C$19+Supuestos!$C$20+Supuestos!$C$21 -> 135 | I15: =B15*Supuestos!$C$11 -> 837.43045 | J15: =E15-F15-G15-H15-I15 -> 3.2557388 | K15: =K14+J15 -> -4846.3848 | L15: =IF(E15=0,0,(E15-F15-G15)/E15) -> 0.65435484
A17: Resumen
A18: MRR al mes 12 (€) | B18: =E15 -> 1491.0659
A19: ARR (MRR × 12, €) | B19: =B18*12 -> 17892.791
A20: Clientes activos al mes 12 | B20: =D15 -> 48.0989
A21: Resultado acumulado al mes 12 (€) | B21: =K15 -> -4846.3848
A22: Primer mes con resultado mensual positivo | B22: =IFERROR(INDEX(A4:A15,MATCH(TRUE(),INDEX(J4:J15>0,0),0)),"no en 12 meses") -> 12
A23: Ingreso medio por cliente (€/mes) | B23: =((1-Supuestos!$C$8)*Supuestos!$C$9+Supuestos!$C$8*Supuestos!$C$10) -> 31
A24: Recuperación del coste de adquisición (meses) | B24: =IFERROR(Supuestos!$C$11/(((1-Supuestos!$C$8)*Supuestos!$C$9+Supuestos!$C$8*Supuestos!$C$10)*(1-Supuestos!$C$14)-Supuestos!$C$15-Supuestos!$C$12/60*Supuestos!$C$13),"n/d") -> 4.4367759

Sheet Optimista
A1: Escenario Optimista · 12 primeros meses
A3: Mes | B3: Altas | C3: Bajas | D3: Clientes activos | E3: MRR (€) | F3: Comisiones de cobro (€) | G3: Soporte (€) | H3: Costes fijos (€) | I3: Adquisición (€) | J3: Resultado del mes (€) | K3: Resultado acumulado (€) | L3: Margen bruto (%)
A4: 1 | B4: =Supuestos!$D$5*(1+Supuestos!$D$6)^(1-1) -> 4 | C4: =0 -> 0 | D4: =B4-C4 -> 4 | E4: =D4*((1-Supuestos!$D$8)*Supuestos!$D$9+Supuestos!$D$8*Supuestos!$D$10) -> 133.6 | F4: =E4*Supuestos!$D$14+D4*Supuestos!$D$15 -> 3.004 | G4: =D4*Supuestos!$D$12/60*Supuestos!$D$13 -> 26.666667 | H4: =Supuestos!$D$16+Supuestos!$D$17+Supuestos!$D$18+Supuestos!$D$19+Supuestos!$D$20+Supuestos!$D$21 -> 135 | I4: =B4*Supuestos!$D$11 -> 240 | J4: =E4-F4-G4-H4-I4-Supuestos!$D$22 -> -3271.0707 | K4: =J4 -> -3271.0707 | L4: =IF(E4=0,0,(E4-F4-G4)/E4) -> 0.77791417
A5: 2 | B5: =Supuestos!$D$5*(1+Supuestos!$D$6)^(2-1) -> 4.8 | C5: =D4*Supuestos!$D$7 -> 0.12 | D5: =D4+B5-C5 -> 8.68 | E5: =D5*((1-Supuestos!$D$8)*Supuestos!$D$9+Supuestos!$D$8*Supuestos!$D$10) -> 289.912 | F5: =E5*Supuestos!$D$14+D5*Supuestos!$D$15 -> 6.51868 | G5: =D5*Supuestos!$D$12/60*Supuestos!$D$13 -> 57.866667 | H5: =Supuestos!$D$16+Supuestos!$D$17+Supuestos!$D$18+Supuestos!$D$19+Supuestos!$D$20+Supuestos!$D$21 -> 135 | I5: =B5*Supuestos!$D$11 -> 288 | J5: =E5-F5-G5-H5-I5 -> -197.47335 | K5: =K4+J5 -> -3468.544 | L5: =IF(E5=0,0,(E5-F5-G5)/E5) -> 0.77791417
A6: 3 | B6: =Supuestos!$D$5*(1+Supuestos!$D$6)^(3-1) -> 5.76 | C6: =D5*Supuestos!$D$7 -> 0.2604 | D6: =D5+B6-C6 -> 14.1796 | E6: =D6*((1-Supuestos!$D$8)*Supuestos!$D$9+Supuestos!$D$8*Supuestos!$D$10) -> 473.59864 | F6: =E6*Supuestos!$D$14+D6*Supuestos!$D$15 -> 10.64888 | G6: =D6*Supuestos!$D$12/60*Supuestos!$D$13 -> 94.530667 | H6: =Supuestos!$D$16+Supuestos!$D$17+Supuestos!$D$18+Supuestos!$D$19+Supuestos!$D$20+Supuestos!$D$21 -> 135 | I6: =B6*Supuestos!$D$11 -> 345.6 | J6: =E6-F6-G6-H6-I6 -> -112.18091 | K6: =K5+J6 -> -3580.7249 | L6: =IF(E6=0,0,(E6-F6-G6)/E6) -> 0.77791417
A7: 4 | B7: =Supuestos!$D$5*(1+Supuestos!$D$6)^(4-1) -> 6.912 | C7: =D6*Supuestos!$D$7 -> 0.425388 | D7: =D6+B7-C7 -> 20.666212 | E7: =D7*((1-Supuestos!$D$8)*Supuestos!$D$9+Supuestos!$D$8*Supuestos!$D$10) -> 690.25148 | F7: =E7*Supuestos!$D$14+D7*Supuestos!$D$15 -> 15.520325 | G7: =D7*Supuestos!$D$12/60*Supuestos!$D$13 -> 137.77475 | H7: =Supuestos!$D$16+Supuestos!$D$17+Supuestos!$D$18+Supuestos!$D$19+Supuestos!$D$20+Supuestos!$D$21 -> 135 | I7: =B7*Supuestos!$D$11 -> 414.72 | J7: =E7-F7-G7-H7-I7 -> -12.763591 | K7: =K6+J7 -> -3593.4885 | L7: =IF(E7=0,0,(E7-F7-G7)/E7) -> 0.77791417
A8: 5 | B8: =Supuestos!$D$5*(1+Supuestos!$D$6)^(5-1) -> 8.2944 | C8: =D7*Supuestos!$D$7 -> 0.61998636 | D8: =D7+B8-C8 -> 28.340626 | E8: =D8*((1-Supuestos!$D$8)*Supuestos!$D$9+Supuestos!$D$8*Supuestos!$D$10) -> 946.5769 | F8: =E8*Supuestos!$D$14+D8*Supuestos!$D$15 -> 21.28381 | G8: =D8*Supuestos!$D$12/60*Supuestos!$D$13 -> 188.9375 | H8: =Supuestos!$D$16+Supuestos!$D$17+Supuestos!$D$18+Supuestos!$D$19+Supuestos!$D$20+Supuestos!$D$21 -> 135 | I8: =B8*Supuestos!$D$11 -> 497.664 | J8: =E8-F8-G8-H8-I8 -> 103.69158 | K8: =K7+J8 -> -3489.7969 | L8: =IF(E8=0,0,(E8-F8-G8)/E8) -> 0.77791417
A9: 6 | B9: =Supuestos!$D$5*(1+Supuestos!$D$6)^(6-1) -> 9.95328 | C9: =D8*Supuestos!$D$7 -> 0.85021877 | D9: =D8+B9-C9 -> 37.443687 | E9: =D9*((1-Supuestos!$D$8)*Supuestos!$D$9+Supuestos!$D$8*Supuestos!$D$10) -> 1250.6191 | F9: =E9*Supuestos!$D$14+D9*Supuestos!$D$15 -> 28.120209 | G9: =D9*Supuestos!$D$12/60*Supuestos!$D$13 -> 249.62458 | H9: =Supuestos!$D$16+Supuestos!$D$17+Supuestos!$D$18+Supuestos!$D$19+Supuestos!$D$20+Supuestos!$D$21 -> 135 | I9: =B9*Supuestos!$D$11 -> 597.1968 | J9: =E9-F9-G9-H9-I9 -> 240.67755 | K9: =K8+J9 -> -3249.1194 | L9: =IF(E9=0,0,(E9-F9-G9)/E9) -> 0.77791417
A10: 7 | B10: =Supuestos!$D$5*(1+Supuestos!$D$6)^(7-1) -> 11.943936 | C10: =D9*Supuestos!$D$7 -> 1.1233106 | D10: =D9+B10-C10 -> 48.264312 | E10: =D10*((1-Supuestos!$D$8)*Supuestos!$D$9+Supuestos!$D$8*Supuestos!$D$10) -> 1612.028 | F10: =E10*Supuestos!$D$14+D10*Supuestos!$D$15 -> 36.246499 | G10: =D10*Supuestos!$D$12/60*Supuestos!$D$13 -> 321.76208 | H10: =Supuestos!$D$16+Supuestos!$D$17+Supuestos!$D$18+Supuestos!$D$19+Supuestos!$D$20+Supuestos!$D$21 -> 135 | I10: =B10*Supuestos!$D$11 -> 716.63616 | J10: =E10-F10-G10-H10-I10 -> 402.38329 | K10: =K9+J10 -> -2846.7361 | L10: =IF(E10=0,0,(E10-F10-G10)/E10) -> 0.77791417
A11: 8 | B11: =Supuestos!$D$5*(1+Supuestos!$D$6)^(8-1) -> 14.332723 | C11: =D10*Supuestos!$D$7 -> 1.4479294 | D11: =D10+B11-C11 -> 61.149106 | E11: =D11*((1-Supuestos!$D$8)*Supuestos!$D$9+Supuestos!$D$8*Supuestos!$D$10) -> 2042.3801 | F11: =E11*Supuestos!$D$14+D11*Supuestos!$D$15 -> 45.922979 | G11: =D11*Supuestos!$D$12/60*Supuestos!$D$13 -> 407.66071 | H11: =Supuestos!$D$16+Supuestos!$D$17+Supuestos!$D$18+Supuestos!$D$19+Supuestos!$D$20+Supuestos!$D$21 -> 135 | I11: =B11*Supuestos!$D$11 -> 859.96339 | J11: =E11-F11-G11-H11-I11 -> 593.83307 | K11: =K10+J11 -> -2252.903 | L11: =IF(E11=0,0,(E11-F11-G11)/E11) -> 0.77791417
A12: 9 | B12: =Supuestos!$D$5*(1+Supuestos!$D$6)^(9-1) -> 17.199268 | C12: =D11*Supuestos!$D$7 -> 1.8344732 | D12: =D11+B12-C12 -> 76.513901 | E12: =D12*((1-Supuestos!$D$8)*Supuestos!$D$9+Supuestos!$D$8*Supuestos!$D$10) -> 2555.5643 | F12: =E12*Supuestos!$D$14+D12*Supuestos!$D$15 -> 57.461939 | G12: =D12*Supuestos!$D$12/60*Supuestos!$D$13 -> 510.09267 | H12: =Supuestos!$D$16+Supuestos!$D$17+Supuestos!$D$18+Supuestos!$D$19+Supuestos!$D$20+Supuestos!$D$21 -> 135 | I12: =B12*Supuestos!$D$11 -> 1031.9561 | J12: =E12-F12-G12-H12-I12 -> 821.0536 | K12: =K11+J12 -> -1431.8494 | L12: =IF(E12=0,0,(E12-F12-G12)/E12) -> 0.77791417
A13: 10 | B13: =Supuestos!$D$5*(1+Supuestos!$D$6)^(10-1) -> 20.639121 | C13: =D12*Supuestos!$D$7 -> 2.295417 | D13: =D12+B13-C13 -> 94.857605 | E13: =D13*((1-Supuestos!$D$8)*Supuestos!$D$9+Supuestos!$D$8*Supuestos!$D$10) -> 3168.244 | F13: =E13*Supuestos!$D$14+D13*Supuestos!$D$15 -> 71.238061 | G13: =D13*Supuestos!$D$12/60*Supuestos!$D$13 -> 632.38403 | H13: =Supuestos!$D$16+Supuestos!$D$17+Supuestos!$D$18+Supuestos!$D$19+Supuestos!$D$20+Supuestos!$D$21 -> 135 | I13: =B13*Supuestos!$D$11 -> 1238.3473 | J13: =E13-F13-G13-H13-I13 -> 1091.2746 | K13: =K12+J13 -> -340.57478 | L13: =IF(E13=0,0,(E13-F13-G13)/E13) -> 0.77791417
A14: 11 | B14: =Supuestos!$D$5*(1+Supuestos!$D$6)^(11-1) -> 24.766946 | C14: =D13*Supuestos!$D$7 -> 2.8457282 | D14: =D13+B14-C14 -> 116.77882 | E14: =D14*((1-Supuestos!$D$8)*Supuestos!$D$9+Supuestos!$D$8*Supuestos!$D$10) -> 3900.4127 | F14: =E14*Supuestos!$D$14+D14*Supuestos!$D$15 -> 87.700896 | G14: =D14*Supuestos!$D$12/60*Supuestos!$D$13 -> 778.52548 | H14: =Supuestos!$D$16+Supuestos!$D$17+Supuestos!$D$18+Supuestos!$D$19+Supuestos!$D$20+Supuestos!$D$21 -> 135 | I14: =B14*Supuestos!$D$11 -> 1486.0167 | J14: =E14-F14-G14-H14-I14 -> 1413.1696 | K14: =K13+J14 -> 1072.5948 | L14: =IF(E14=0,0,(E14-F14-G14)/E14) -> 0.77791417
A15: 12 | B15: =Supuestos!$D$5*(1+Supuestos!$D$6)^(12-1) -> 29.720335 | C15: =D14*Supuestos!$D$7 -> 3.5033647 | D15: =D14+B15-C15 -> 142.99579 | E15: =D15*((1-Supuestos!$D$8)*Supuestos!$D$9+Supuestos!$D$8*Supuestos!$D$10) -> 4776.0595 | F15: =E15*Supuestos!$D$14+D15*Supuestos!$D$15 -> 107.38984 | G15: =D15*Supuestos!$D$12/60*Supuestos!$D$13 -> 953.30529 | H15: =Supuestos!$D$16+Supuestos!$D$17+Supuestos!$D$18+Supuestos!$D$19+Supuestos!$D$20+Supuestos!$D$21 -> 135 | I15: =B15*Supuestos!$D$11 -> 1783.2201 | J15: =E15-F15-G15-H15-I15 -> 1797.1443 | K15: =K14+J15 -> 2869.739 | L15: =IF(E15=0,0,(E15-F15-G15)/E15) -> 0.77791417
A17: Resumen
A18: MRR al mes 12 (€) | B18: =E15 -> 4776.0595
A19: ARR (MRR × 12, €) | B19: =B18*12 -> 57312.714
A20: Clientes activos al mes 12 | B20: =D15 -> 142.99579
A21: Resultado acumulado al mes 12 (€) | B21: =K15 -> 2869.739
A22: Primer mes con resultado mensual positivo | B22: =IFERROR(INDEX(A4:A15,MATCH(TRUE(),INDEX(J4:J15>0,0),0)),"no en 12 meses") -> 5
A23: Ingreso medio por cliente (€/mes) | B23: =((1-Supuestos!$D$8)*Supuestos!$D$9+Supuestos!$D$8*Supuestos!$D$10) -> 33.4
A24: Recuperación del coste de adquisición (meses) | B24: =IFERROR(Supuestos!$D$11/(((1-Supuestos!$D$8)*Supuestos!$D$9+Supuestos!$D$8*Supuestos!$D$10)*(1-Supuestos!$D$14)-Supuestos!$D$15-Supuestos!$D$12/60*Supuestos!$D$13),"n/d") -> 2.3092614
